setup.py
django_barricade/__init__.py
django_barricade/middleware.py
django_barricade/models.py
django_barricade.egg-info/PKG-INFO
django_barricade.egg-info/SOURCES.txt
django_barricade.egg-info/dependency_links.txt
django_barricade.egg-info/not-zip-safe
django_barricade.egg-info/requires.txt
django_barricade.egg-info/top_level.txt