Metadata-Version: 1.1
Name: django-barricade
Version: 0.1.0
Summary: Simulate a slow connection
Home-page: http://github.com/wancw/django-barricade
Author: WanCW
Author-email: wancw.wang@gmail.com
License: MIT
Keywords: django,network
Platform: UNKNOWN
Classifier: Programming Language :: Python
Classifier: Topic :: Software Development :: Libraries :: Python Modules
Classifier: Framework :: Django
Classifier: Environment :: Web Environment
